text2array/__init__.py
text2array/batches.py
text2array/iterators.py
text2array/py.typed
text2array/samples.py
text2array/vocab.py
text2array-0.2.1.dist-info/LICENSE
text2array-0.2.1.dist-info/WHEEL
text2array-0.2.1.dist-info/METADATA
text2array-0.2.1.dist-info/RECORD
