Metadata-Version: 2.1
Name: text2array
Version: 0.2.1
Summary: Convert your NLP text data to arrays!
Home-page: https://github.com/kmkurn/text2array
License: UNKNOWN
Author: Kemal Kurniawan
Author-email: kemal@kkurniawan.com
Requires-Python: >=3.6,<4
Classifier: Development Status :: 4 - Beta
Classifier: Intended Audience :: Developers
Classifier: Intended Audience :: Science/Research
Classifier: License :: OSI Approved :: Apache Software License
Classifier: Programming Language :: Python :: 3.6
Classifier: Programming Language :: Python :: 3.7
Classifier: Topic :: Scientific/Engineering :: Artificial Intelligence
Requires-Dist: numpy
Requires-Dist: tqdm
Requires-Dist: ordered-set ~=3.1.1
Requires-Dist: flake8 ; extra == "dev"
Requires-Dist: mypy ~=0.770 ; extra == "dev"
Requires-Dist: black ~=19.10b0 ; extra == "dev"
Requires-Dist: Sphinx ~=1.8.3 ; extra == "doc"
Requires-Dist: sphinx_rtd_theme ; extra == "doc"
Requires-Dist: sphinx-autodoc-typehints ~=1.6.0 ; extra == "doc"
Requires-Dist: pytest ~=5.2.1 ; extra == "test"
Requires-Dist: pytest-cov ; extra == "test"
Project-URL: Documentation, https://text2array.readthedocs.io
Provides-Extra: dev
Provides-Extra: doc
Provides-Extra: test
